[
    {
        "thumbnail": "http://i.imgur.com/5nc1ysQ.png",
        "url": "http://vimeo.com/89134214"
    },
    {
        "thumbnail": "images/photos/mikko_thumb.jpg",
        "url": "http://i.imgur.com/wBSU7mr.jpg"
    },
    {
        "thumbnail": "images/photos/sailship_thumb.jpg",
        "url": "http://i.imgur.com/vKjccCK.jpg"
    },
    {
        "thumbnail": "images/photos/julia-sunglass2_thumb.jpg",
        "url": "http://i.imgur.com/oSwPEgV.jpg"
    },
    {
        "thumbnail": "images/photos/harbor_thumb.jpg",
        "url": "http://i.imgur.com/LVsNsiZ.jpg"
    },
    {
        "thumbnail": "images/photos/julia-sunglass_thumb.jpg",
        "url": "http://i.imgur.com/HpyJZb2.jpg"
    },
    {
        "thumbnail": "images/photos/cake_thumb.jpg",
        "url": "http://i.imgur.com/Eg2ySgE.jpg"
    },
    {
        "thumbnail": "images/photos/bicycle_thumb.jpg",
        "url": "http://i.imgur.com/LnDcKpg.jpg"
    },
    {
        "thumbnail": "images/photos/hameenkatu_thumb.jpg",
        "url": "http://i.imgur.com/nFxPoIV.jpg"
    },
    {
        "thumbnail": "images/photos/dolphin_thumb.jpg",
        "url": "http://i.imgur.com/q10zzUg.jpg"
    },
    {
        "thumbnail": "images/photos/ilkka_thumb.jpg",
        "url": "http://i.imgur.com/jXAGptw.jpg"
    },
    {
        "thumbnail": "images/photos/julia-dollar_thumb.jpg",
        "url": "http://i.imgur.com/GtYGBGx.jpg"
    }
]